pyvi/ViDiac.py
pyvi/ViPosTagger.py
pyvi/ViTokenizer.py
pyvi/ViUtils.py
pyvi/__init__.py
pyvi/train_tokenizer.py
pyvi/models/pyvi.pkl
pyvi/models/pyvi3.pkl
pyvi/models/pyvipos.pkl
pyvi/models/pyvipos3.pkl
pyvi/models/vidiac.crfsuite
pyvi/models/words.txt
pyvi-0.1.1.dist-info/LICENSE.txt
pyvi-0.1.1.dist-info/METADATA
pyvi-0.1.1.dist-info/WHEEL
pyvi-0.1.1.dist-info/entry_points.txt
pyvi-0.1.1.dist-info/top_level.txt
pyvi-0.1.1.dist-info/RECORD
