Metadata-Version: 2.1
Name: pyvi
Version: 0.1.1
Summary: Python Vietnamese Toolkit
Home-page: https://github.com/trungtv/pyvi
Author: Viet-Trung Tran
Author-email: trungtv@soict.hust.edu.vn
License: MIT
Keywords: Vietnamese natural language processing
Platform: UNKNOWN
Classifier: Development Status :: 3 - Alpha
Classifier: Intended Audience :: Developers
Classifier: Natural Language :: Vietnamese
Classifier: License :: OSI Approved :: MIT License
Classifier: Programming Language :: Python :: 2
Classifier: Programming Language :: Python :: 2.6
Classifier: Programming Language :: Python :: 2.7
Classifier: Programming Language :: Python :: 3
Provides-Extra: dev
Provides-Extra: test
License-File: LICENSE.txt
